orm_bitrix24/entity/__init__.py
orm_bitrix24/entity/base.py
orm_bitrix24/entity/base.pyi
orm_bitrix24/entity/company.py
orm_bitrix24/entity/contact.py
orm_bitrix24/entity/deal.py
orm_bitrix24/entity/deal.pyi
orm_bitrix24/entity/lead.py
orm_bitrix24/entity/note.py
test_publish2-0.1.2.dist-info/METADATA
test_publish2-0.1.2.dist-info/WHEEL
test_publish2-0.1.2.dist-info/top_level.txt
test_publish2-0.1.2.dist-info/RECORD
