Metadata-Version: 2.4
Name: test_publish2
Version: 0.1.2
Summary: Test publish2
Project-URL: Homepage, https://github.com/darkClaw921/test_publish
Project-URL: Documentation, https://github.com/darkClaw921/test_publish
Project-URL: Repository, https://github.com/darkClaw921/test_publish.git
Project-URL: Bug Tracker, https://github.com/darkClaw921/test_publish/issues
Project-URL: Changelog, https://github.com/darkClaw921/test_publish/blob/master/CHANGELOG.md
Requires-Python: >=3.12
Requires-Dist: fast-bitrix24
Requires-Dist: python-dotenv
